<?xml version = '1.0' encoding = 'UTF-8'?>
<Relation class="oracle.dbtools.crest.model.design.logical.Relation" name="Relation_6" directorySegmentName="seg_0" id="F99D6831-068D-6BC5-3209-E35FA40A4BBB">
<createdBy>56946</createdBy>
<createdTime>2022-08-24 19:39:07 UTC</createdTime>
<ownerDesignName>BD_CONSERVADOR</ownerDesignName>
<engineerTo>
<item key="8AEFACBD-2A69-3012-8741-E631DEC6BE9D" value="true"/>
</engineerTo>
<sourcePk>960526B2-354C-0926-169E-3B2313460CDA</sourcePk>
<identifying>false</identifying>
<optionalSource>false</optionalSource>
<optionalTarget>false</optionalTarget>
<sourceCardinality>1</sourceCardinality>
<sourceEntity>3613224B-E8EB-0377-BCB6-82CCCC39BA48</sourceEntity>
<targetCardinalityString>*</targetCardinalityString>
<targetEntity>72E180CD-6BAF-470B-C1BE-98B20BC5E640</targetEntity>
<transferable>true</transferable>
<deleteRule>NO ACTION</deleteRule>
</Relation>